LICENSE
README.md
setup.py
kgn/__init__.py
kgn/__main__.py
kgn/cache.py
kgn/cli.py
kgn/colorize.py
kgn/kgn.py
kgn/kgnutils.py
kgn/relationships.py
kgn/sparql.py
kgn/textui.py
kgn.egg-info/PKG-INFO
kgn.egg-info/SOURCES.txt
kgn.egg-info/dependency_links.txt
kgn.egg-info/entry_points.txt
kgn.egg-info/requires.txt
kgn.egg-info/top_level.txt