Metadata-Version: 2.1
Name: kgn
Version: 0.46
Summary: Interactive exploration of Knowledge Graphs using natural language
Home-page: https://github.com/mark-watson/kgn
Author: Mark Watson
License: Apache License, Version 2.0
Project-URL: Issues, https://github.com/mark-watson/kgn/issues
Project-URL: CI, https://github.com/mark-watson/kgn/actions
Project-URL: Changelog, https://github.com/mark-watson/kgn/releases
Requires-Python: >=3.7
Provides-Extra: test
License-File: LICENSE
